LICENSE
README.md
setup.py
tailwindpie/__init__.py
tailwindpie/__main__.py
tailwindpie/main.py
tailwindpie.egg-info/PKG-INFO
tailwindpie.egg-info/SOURCES.txt
tailwindpie.egg-info/dependency_links.txt
tailwindpie.egg-info/entry_points.txt
tailwindpie.egg-info/requires.txt
tailwindpie.egg-info/top_level.txt